exporgo/__init__.py
exporgo/__main__.py
exporgo/_color.py
exporgo/_docs.py
exporgo/_generics.py
exporgo/_logging.py
exporgo/_version.py
exporgo/exceptions.py
exporgo/io.py
exporgo/tools.py
exporgo/types.py
exporgo/validators.py
exporgo/automation/__init__.py
exporgo/automation/elements.py
exporgo/automation/lock.py
exporgo/automation/manager.py
exporgo/automation/scheduler.py
exporgo/automation/task.py
exporgo/organization/__init__.py
exporgo/organization/experiment.py
exporgo/organization/files.py
exporgo/organization/pipeline.py
exporgo/organization/step.py
exporgo/organization/study.py
exporgo/organization/subject.py
exporgo/registry/__init__.py
exporgo/registry/registered_experiments.json
exporgo/registry/registered_steps.json
exporgo/schemas/experiment_config.json
exporgo/schemas/pipeline_config.json
exporgo/schemas/step_config.json
exporgo-0.2.8.dist-info/LICENSE
exporgo-0.2.8.dist-info/METADATA
exporgo-0.2.8.dist-info/WHEEL
exporgo-0.2.8.dist-info/entry_points.txt
exporgo-0.2.8.dist-info/top_level.txt
exporgo-0.2.8.dist-info/RECORD
